[{"ID":1,"PROGRAMA":"Ingeniería Electrónica (Nocturno)","0":1.0,"I":20,"II":69,"III":141.0,"IV":87.0,"V":18.0,"VI":3.0,"SEMESTRE":"2010-1"},{"ID":2,"PROGRAMA":"Ingeniería Eléctrica","0":null,"I":105,"II":265,"III":256.0,"IV":107.0,"V":21.0,"VI":4.0,"SEMESTRE":"2010-1"},{"ID":3,"PROGRAMA":"Ingeniería Física","0":null,"I":53,"II":88,"III":81.0,"IV":27.0,"V":13.0,"VI":2.0,"SEMESTRE":"2010-1"},{"ID":4,"PROGRAMA":"Ingeniería de Sistemas y Computación","0":null,"I":79,"II":250,"III":241.0,"IV":90.0,"V":18.0,"VI":6.0,"SEMESTRE":"2010-1"},{"ID":5,"PROGRAMA":"Ingeniería de Sistemas y Computación (Nocturno)","0":1.0,"I":23,"II":77,"III":112.0,"IV":68.0,"V":16.0,"VI":1.0,"SEMESTRE":"2010-1"},{"ID":6,"PROGRAMA":"Ingeniería Electrónica (Nocturno)","0":1.0,"I":23,"II":72,"III":129.0,"IV":89.0,"V":15.0,"VI":2.0,"SEMESTRE":"2010-2"},{"ID":7,"PROGRAMA":"Ingeniería Eléctrica","0":null,"I":121,"II":265,"III":249.0,"IV":97.0,"V":22.0,"VI":4.0,"SEMESTRE":"2010-2"},{"ID":8,"PROGRAMA":"Ingeniería Física","0":null,"I":40,"II":78,"III":64.0,"IV":25.0,"V":11.0,"VI":2.0,"SEMESTRE":"2010-2"},{"ID":9,"PROGRAMA":"Ingeniería de Sistemas y Computación","0":null,"I":77,"II":249,"III":221.0,"IV":87.0,"V":21.0,"VI":7.0,"SEMESTRE":"2010-2"},{"ID":10,"PROGRAMA":"Ingeniería de Sistemas y Computación (Nocturno)","0":1.0,"I":25,"II":79,"III":96.0,"IV":65.0,"V":18.0,"VI":2.0,"SEMESTRE":"2010-2"},{"ID":11,"PROGRAMA":"Ingeniería Electrónica (Nocturno)","0":1.0,"I":24,"II":73,"III":115.0,"IV":90.0,"V":18.0,"VI":2.0,"SEMESTRE":"2011-1"},{"ID":12,"PROGRAMA":"Ingeniería Eléctrica","0":null,"I":133,"II":280,"III":237.0,"IV":96.0,"V":20.0,"VI":2.0,"SEMESTRE":"2011-1"},{"ID":13,"PROGRAMA":"Ingeniería Física","0":null,"I":50,"II":102,"III":81.0,"IV":27.0,"V":12.0,"VI":2.0,"SEMESTRE":"2011-1"},{"ID":14,"PROGRAMA":"Ingeniería de Sistemas y Computación","0":1.0,"I":91,"II":276,"III":213.0,"IV":84.0,"V":23.0,"VI":9.0,"SEMESTRE":"2011-1"},{"ID":15,"PROGRAMA":"Ingeniería de Sistemas y Computación (Nocturno)","0":1.0,"I":19,"II":97,"III":102.0,"IV":67.0,"V":19.0,"VI":4.0,"SEMESTRE":"2011-1"},{"ID":16,"PROGRAMA":"Ingeniería Electrónica (Nocturno)","0":1.0,"I":25,"II":79,"III":123.0,"IV":82.0,"V":17.0,"VI":1.0,"SEMESTRE":"2011-2"},{"ID":17,"PROGRAMA":"Ingeniería Eléctrica","0":null,"I":159,"II":297,"III":243.0,"IV":90.0,"V":17.0,"VI":2.0,"SEMESTRE":"2011-2"},{"ID":18,"PROGRAMA":"Ingeniería Física","0":null,"I":45,"II":89,"III":67.0,"IV":17.0,"V":8.0,"VI":2.0,"SEMESTRE":"2011-2"},{"ID":19,"PROGRAMA":"Ingeniería de Sistemas y Computación","0":null,"I":104,"II":297,"III":205.0,"IV":74.0,"V":20.0,"VI":7.0,"SEMESTRE":"2011-2"},{"ID":20,"PROGRAMA":"Ingeniería de Sistemas y Computación (Nocturno)","0":1.0,"I":25,"II":88,"III":100.0,"IV":68.0,"V":17.0,"VI":4.0,"SEMESTRE":"2011-2"},{"ID":21,"PROGRAMA":"Ingeniería Electrónica (Nocturno)","0":1.0,"I":24,"II":79,"III":99.0,"IV":77.0,"V":17.0,"VI":2.0,"SEMESTRE":"2012-1"},{"ID":22,"PROGRAMA":"Ingeniería Eléctrica","0":null,"I":161,"II":301,"III":242.0,"IV":76.0,"V":17.0,"VI":4.0,"SEMESTRE":"2012-1"},{"ID":23,"PROGRAMA":"Ingeniería Física","0":null,"I":55,"II":125,"III":85.0,"IV":21.0,"V":10.0,"VI":1.0,"SEMESTRE":"2012-1"},{"ID":24,"PROGRAMA":"Ingeniería de Sistemas y Computación","0":null,"I":105,"II":276,"III":186.0,"IV":68.0,"V":18.0,"VI":4.0,"SEMESTRE":"2012-1"},{"ID":25,"PROGRAMA":"Ingeniería de Sistemas y Computación (Nocturno)","0":1.0,"I":22,"II":90,"III":93.0,"IV":56.0,"V":15.0,"VI":4.0,"SEMESTRE":"2012-1"},{"ID":26,"PROGRAMA":"Ingeniería Electrónica (Nocturno)","0":1.0,"I":18,"II":87,"III":92.0,"IV":77.0,"V":16.0,"VI":1.0,"SEMESTRE":"2012-2"},{"ID":27,"PROGRAMA":"Ingeniería Eléctrica","0":null,"I":183,"II":339,"III":240.0,"IV":84.0,"V":18.0,"VI":5.0,"SEMESTRE":"2012-2"},{"ID":28,"PROGRAMA":"Ingeniería Física","0":null,"I":45,"II":99,"III":72.0,"IV":18.0,"V":11.0,"VI":1.0,"SEMESTRE":"2012-2"},{"ID":29,"PROGRAMA":"Ingeniería de Sistemas y Computación","0":null,"I":119,"II":291,"III":163.0,"IV":62.0,"V":18.0,"VI":6.0,"SEMESTRE":"2012-2"},{"ID":30,"PROGRAMA":"Ingeniería de Sistemas y Computación (Nocturno)","0":1.0,"I":21,"II":98,"III":87.0,"IV":58.0,"V":13.0,"VI":1.0,"SEMESTRE":"2012-2"},{"ID":31,"PROGRAMA":"Ingeniería Electrónica (Nocturno)","0":1.0,"I":16,"II":88,"III":95.0,"IV":77.0,"V":11.0,"VI":2.0,"SEMESTRE":"2013-1"},{"ID":32,"PROGRAMA":"Ingeniería Eléctrica","0":null,"I":183,"II":365,"III":244.0,"IV":85.0,"V":19.0,"VI":6.0,"SEMESTRE":"2013-1"},{"ID":33,"PROGRAMA":"Ingeniería Física","0":null,"I":54,"II":128,"III":87.0,"IV":24.0,"V":10.0,"VI":null,"SEMESTRE":"2013-1"},{"ID":34,"PROGRAMA":"Ingeniería de Sistemas y Computación","0":null,"I":118,"II":300,"III":180.0,"IV":68.0,"V":19.0,"VI":4.0,"SEMESTRE":"2013-1"},{"ID":35,"PROGRAMA":"Ingeniería de Sistemas y Computación (Nocturno)","0":1.0,"I":27,"II":100,"III":86.0,"IV":59.0,"V":12.0,"VI":null,"SEMESTRE":"2013-1"},{"ID":36,"PROGRAMA":"Ingeniería Electrónica (Nocturno)","0":1.0,"I":16,"II":73,"III":85.0,"IV":75.0,"V":11.0,"VI":3.0,"SEMESTRE":"2013-2"},{"ID":37,"PROGRAMA":"Ingeniería Eléctrica","0":null,"I":189,"II":386,"III":243.0,"IV":75.0,"V":17.0,"VI":5.0,"SEMESTRE":"2013-2"},{"ID":38,"PROGRAMA":"Ingeniería Física","0":null,"I":49,"II":103,"III":72.0,"IV":16.0,"V":8.0,"VI":null,"SEMESTRE":"2013-2"},{"ID":39,"PROGRAMA":"Ingeniería de Sistemas y Computación","0":null,"I":124,"II":301,"III":171.0,"IV":65.0,"V":17.0,"VI":5.0,"SEMESTRE":"2013-2"},{"ID":40,"PROGRAMA":"Ingeniería de Sistemas y Computación (Nocturno)","0":1.0,"I":25,"II":97,"III":88.0,"IV":54.0,"V":11.0,"VI":null,"SEMESTRE":"2013-2"},{"ID":41,"PROGRAMA":"Ingeniería Electrónica (Nocturno)","0":1.0,"I":15,"II":94,"III":89.0,"IV":78.0,"V":12.0,"VI":3.0,"SEMESTRE":"2014-1"},{"ID":42,"PROGRAMA":"Ingeniería Eléctrica","0":null,"I":222,"II":426,"III":262.0,"IV":80.0,"V":17.0,"VI":6.0,"SEMESTRE":"2014-1"},{"ID":43,"PROGRAMA":"Ingeniería Física","0":null,"I":73,"II":147,"III":84.0,"IV":22.0,"V":7.0,"VI":null,"SEMESTRE":"2014-1"},{"ID":44,"PROGRAMA":"Ingeniería de Sistemas y Computación","0":null,"I":136,"II":338,"III":188.0,"IV":56.0,"V":16.0,"VI":3.0,"SEMESTRE":"2014-1"},{"ID":45,"PROGRAMA":"Ingeniería de Sistemas y Computación (Nocturno)","0":1.0,"I":28,"II":106,"III":90.0,"IV":55.0,"V":10.0,"VI":null,"SEMESTRE":"2014-1"},{"ID":46,"PROGRAMA":"Ingeniería Electrónica (Nocturno)","0":1.0,"I":11,"II":89,"III":65.0,"IV":62.0,"V":8.0,"VI":1.0,"SEMESTRE":"2014-2"},{"ID":47,"PROGRAMA":"Ingeniería Eléctrica","0":null,"I":224,"II":418,"III":255.0,"IV":65.0,"V":12.0,"VI":5.0,"SEMESTRE":"2014-2"},{"ID":48,"PROGRAMA":"Ingeniería Física","0":null,"I":59,"II":127,"III":71.0,"IV":16.0,"V":7.0,"VI":null,"SEMESTRE":"2014-2"},{"ID":49,"PROGRAMA":"Ingeniería de Sistemas y Computación","0":null,"I":124,"II":329,"III":184.0,"IV":56.0,"V":16.0,"VI":3.0,"SEMESTRE":"2014-2"},{"ID":50,"PROGRAMA":"Ingeniería de Sistemas y Computación (Nocturno)","0":1.0,"I":22,"II":104,"III":77.0,"IV":47.0,"V":5.0,"VI":null,"SEMESTRE":"2014-2"},{"ID":51,"PROGRAMA":"Ingeniería Electrónica (Nocturno)","0":1.0,"I":21,"II":114,"III":80.0,"IV":75.0,"V":9.0,"VI":2.0,"SEMESTRE":"2015-1"},{"ID":52,"PROGRAMA":"Ingeniería Eléctrica","0":null,"I":230,"II":431,"III":237.0,"IV":76.0,"V":13.0,"VI":4.0,"SEMESTRE":"2015-1"},{"ID":53,"PROGRAMA":"Ingeniería Física","0":null,"I":64,"II":159,"III":74.0,"IV":18.0,"V":7.0,"VI":1.0,"SEMESTRE":"2015-1"},{"ID":54,"PROGRAMA":"Ingeniería de Sistemas y Computación","0":null,"I":135,"II":336,"III":179.0,"IV":51.0,"V":12.0,"VI":2.0,"SEMESTRE":"2015-1"},{"ID":55,"PROGRAMA":"Ingeniería de Sistemas y Computación (Nocturno)","0":1.0,"I":29,"II":121,"III":90.0,"IV":56.0,"V":7.0,"VI":null,"SEMESTRE":"2015-1"},{"ID":56,"PROGRAMA":"Ingeniería Electrónica (Nocturno)","0":null,"I":23,"II":110,"III":70.0,"IV":72.0,"V":7.0,"VI":1.0,"SEMESTRE":"2015-2"},{"ID":57,"PROGRAMA":"Ingeniería Eléctrica","0":null,"I":242,"II":448,"III":225.0,"IV":66.0,"V":11.0,"VI":5.0,"SEMESTRE":"2015-2"},{"ID":58,"PROGRAMA":"Ingeniería Física","0":null,"I":63,"II":149,"III":69.0,"IV":13.0,"V":5.0,"VI":1.0,"SEMESTRE":"2015-2"},{"ID":59,"PROGRAMA":"Ingeniería de Sistemas y Computación","0":null,"I":149,"II":333,"III":165.0,"IV":49.0,"V":12.0,"VI":2.0,"SEMESTRE":"2015-2"},{"ID":60,"PROGRAMA":"Ingeniería de Sistemas y Computación (Nocturno)","0":1.0,"I":30,"II":111,"III":91.0,"IV":50.0,"V":8.0,"VI":2.0,"SEMESTRE":"2015-2"},{"ID":61,"PROGRAMA":"Ingeniería Electrónica (Nocturno)","0":null,"I":30,"II":115,"III":74.0,"IV":67.0,"V":3.0,"VI":2.0,"SEMESTRE":"2016-1"},{"ID":62,"PROGRAMA":"Ingeniería Eléctrica","0":1.0,"I":250,"II":451,"III":230.0,"IV":61.0,"V":11.0,"VI":3.0,"SEMESTRE":"2016-1"},{"ID":63,"PROGRAMA":"Ingeniería Física","0":null,"I":89,"II":168,"III":72.0,"IV":13.0,"V":8.0,"VI":1.0,"SEMESTRE":"2016-1"},{"ID":64,"PROGRAMA":"Ingeniería de Sistemas y Computación","0":null,"I":154,"II":356,"III":167.0,"IV":52.0,"V":14.0,"VI":4.0,"SEMESTRE":"2016-1"},{"ID":65,"PROGRAMA":"Ingeniería de Sistemas y Computación (Nocturno)","0":null,"I":37,"II":103,"III":91.0,"IV":52.0,"V":8.0,"VI":7.0,"SEMESTRE":"2016-1"},{"ID":66,"PROGRAMA":"Ingeniería Electrónica (Diurna)","0":null,"I":4,"II":8,"III":3.0,"IV":7.0,"V":1.0,"VI":null,"SEMESTRE":"2016-2"},{"ID":67,"PROGRAMA":"Ingeniería Electrónica (Nocturno)","0":null,"I":21,"II":88,"III":54.0,"IV":59.0,"V":2.0,"VI":2.0,"SEMESTRE":"2016-2"},{"ID":68,"PROGRAMA":"Ingeniería Eléctrica","0":1.0,"I":261,"II":446,"III":204.0,"IV":51.0,"V":12.0,"VI":4.0,"SEMESTRE":"2016-2"},{"ID":69,"PROGRAMA":"Ingeniería Física","0":null,"I":97,"II":170,"III":66.0,"IV":11.0,"V":7.0,"VI":1.0,"SEMESTRE":"2016-2"},{"ID":70,"PROGRAMA":"Ingeniería de Sistemas y Computación","0":null,"I":160,"II":348,"III":160.0,"IV":53.0,"V":13.0,"VI":6.0,"SEMESTRE":"2016-2"},{"ID":71,"PROGRAMA":"Ingeniería de Sistemas y Computación (Nocturno)","0":null,"I":42,"II":116,"III":79.0,"IV":53.0,"V":6.0,"VI":3.0,"SEMESTRE":"2016-2"},{"ID":72,"PROGRAMA":"Ingeniería Electrónica (Diurna)","0":null,"I":12,"II":23,"III":18.0,"IV":13.0,"V":2.0,"VI":null,"SEMESTRE":"2017-1"},{"ID":73,"PROGRAMA":"Ingeniería Electrónica (Nocturno)","0":null,"I":18,"II":76,"III":49.0,"IV":50.0,"V":2.0,"VI":2.0,"SEMESTRE":"2017-1"},{"ID":74,"PROGRAMA":"Ingeniería Eléctrica","0":1.0,"I":268,"II":441,"III":214.0,"IV":55.0,"V":11.0,"VI":4.0,"SEMESTRE":"2017-1"},{"ID":75,"PROGRAMA":"Ingeniería Eléctrica (Básicos ingeniería)","0":null,"I":6,"II":15,"III":1.0,"IV":null,"V":null,"VI":null,"SEMESTRE":"2017-1"},{"ID":76,"PROGRAMA":"Ingeniería Física","0":null,"I":96,"II":182,"III":74.0,"IV":14.0,"V":5.0,"VI":1.0,"SEMESTRE":"2017-1"},{"ID":77,"PROGRAMA":"Ingeniería Física (Básicos ingenieria)","0":null,"I":6,"II":8,"III":2.0,"IV":1.0,"V":null,"VI":null,"SEMESTRE":"2017-1"},{"ID":78,"PROGRAMA":"Ingeniería de Sistemas y Computación","0":null,"I":165,"II":352,"III":159.0,"IV":59.0,"V":14.0,"VI":7.0,"SEMESTRE":"2017-1"},{"ID":79,"PROGRAMA":"Ingeniería de Sistemas y Computación (Básicos ingeniería)","0":null,"I":10,"II":19,"III":1.0,"IV":null,"V":null,"VI":1.0,"SEMESTRE":"2017-1"},{"ID":80,"PROGRAMA":"Ingeniería de Sistemas y Computación (Convenio Cuba)","0":null,"I":12,"II":22,"III":7.0,"IV":4.0,"V":1.0,"VI":null,"SEMESTRE":"2017-1"},{"ID":81,"PROGRAMA":"Ingeniería de Sistemas y Computación (Nocturno)","0":2.0,"I":40,"II":119,"III":76.0,"IV":41.0,"V":7.0,"VI":5.0,"SEMESTRE":"2017-1"},{"ID":82,"PROGRAMA":"Ingeniería Electrónica (Diurna)","0":null,"I":18,"II":27,"III":19.0,"IV":10.0,"V":2.0,"VI":1.0,"SEMESTRE":"2017-2"},{"ID":83,"PROGRAMA":"Ingeniería Electrónica (Nocturno)","0":null,"I":14,"II":66,"III":41.0,"IV":40.0,"V":1.0,"VI":2.0,"SEMESTRE":"2017-2"},{"ID":84,"PROGRAMA":"Ingeniería Eléctrica","0":1.0,"I":289,"II":446,"III":218.0,"IV":50.0,"V":10.0,"VI":4.0,"SEMESTRE":"2017-2"},{"ID":85,"PROGRAMA":"Ingeniería Eléctrica (Básicos ingeniería)","0":null,"I":7,"II":13,"III":null,"IV":null,"V":null,"VI":null,"SEMESTRE":"2017-2"},{"ID":86,"PROGRAMA":"Ingeniería Física","0":null,"I":90,"II":165,"III":78.0,"IV":11.0,"V":5.0,"VI":1.0,"SEMESTRE":"2017-2"},{"ID":87,"PROGRAMA":"Ingeniería Física (Básicos ingenieria)","0":null,"I":6,"II":7,"III":1.0,"IV":1.0,"V":null,"VI":null,"SEMESTRE":"2017-2"},{"ID":88,"PROGRAMA":"Ingeniería de Sistemas y Computación","0":null,"I":171,"II":352,"III":149.0,"IV":64.0,"V":13.0,"VI":7.0,"SEMESTRE":"2017-2"},{"ID":89,"PROGRAMA":"Ingeniería de Sistemas y Computación (Básicos ingeniería)","0":null,"I":9,"II":17,"III":1.0,"IV":null,"V":null,"VI":1.0,"SEMESTRE":"2017-2"},{"ID":90,"PROGRAMA":"Ingeniería de Sistemas y Computación (Convenio Cuba)","0":null,"I":11,"II":19,"III":6.0,"IV":4.0,"V":1.0,"VI":null,"SEMESTRE":"2017-2"},{"ID":91,"PROGRAMA":"Ingeniería de Sistemas y Computación (Nocturno)","0":1.0,"I":41,"II":108,"III":77.0,"IV":44.0,"V":5.0,"VI":2.0,"SEMESTRE":"2017-2"},{"ID":92,"PROGRAMA":"Ingeniería Electrónica (Diurna)","0":null,"I":30,"II":45,"III":30.0,"IV":12.0,"V":3.0,"VI":1.0,"SEMESTRE":"2018-1"},{"ID":93,"PROGRAMA":"Ingeniería Electrónica (Nocturno)","0":null,"I":12,"II":56,"III":34.0,"IV":35.0,"V":1.0,"VI":2.0,"SEMESTRE":"2018-1"},{"ID":94,"PROGRAMA":"Ingeniería Eléctrica","0":1.0,"I":300,"II":431,"III":210.0,"IV":43.0,"V":10.0,"VI":4.0,"SEMESTRE":"2018-1"},{"ID":95,"PROGRAMA":"Ingeniería Eléctrica (Básicos ingeniería)","0":null,"I":7,"II":11,"III":null,"IV":null,"V":null,"VI":null,"SEMESTRE":"2018-1"},{"ID":96,"PROGRAMA":"Ingeniería Física","0":null,"I":100,"II":166,"III":82.0,"IV":8.0,"V":3.0,"VI":1.0,"SEMESTRE":"2018-1"},{"ID":97,"PROGRAMA":"Ingeniería Física (Básicos ingenieria)","0":null,"I":5,"II":7,"III":1.0,"IV":1.0,"V":null,"VI":null,"SEMESTRE":"2018-1"},{"ID":98,"PROGRAMA":"Ingeniería de Sistemas y Computación","0":null,"I":177,"II":353,"III":156.0,"IV":55.0,"V":11.0,"VI":7.0,"SEMESTRE":"2018-1"},{"ID":99,"PROGRAMA":"Ingeniería de Sistemas y Computación (Básicos ingeniería)","0":null,"I":9,"II":13,"III":1.0,"IV":null,"V":null,"VI":1.0,"SEMESTRE":"2018-1"},{"ID":100,"PROGRAMA":"Ingeniería de Sistemas y Computación (Convenio Cuba)","0":null,"I":11,"II":18,"III":6.0,"IV":4.0,"V":1.0,"VI":null,"SEMESTRE":"2018-1"},{"ID":101,"PROGRAMA":"Ingeniería de Sistemas y Computación (Nocturno)","0":null,"I":41,"II":105,"III":81.0,"IV":40.0,"V":7.0,"VI":3.0,"SEMESTRE":"2018-1"},{"ID":102,"PROGRAMA":"Ingeniería Electrónica (Diurna)","0":null,"I":31,"II":47,"III":30.0,"IV":11.0,"V":5.0,"VI":1.0,"SEMESTRE":"2018-2"},{"ID":103,"PROGRAMA":"Ingeniería Electrónica (Nocturno)","0":null,"I":8,"II":48,"III":31.0,"IV":30.0,"V":1.0,"VI":2.0,"SEMESTRE":"2018-2"},{"ID":104,"PROGRAMA":"Ingeniería Eléctrica","0":1.0,"I":299,"II":424,"III":192.0,"IV":43.0,"V":10.0,"VI":1.0,"SEMESTRE":"2018-2"},{"ID":105,"PROGRAMA":"Ingeniería Eléctrica (Básicos ingeniería)","0":null,"I":7,"II":11,"III":null,"IV":null,"V":null,"VI":null,"SEMESTRE":"2018-2"},{"ID":106,"PROGRAMA":"Ingeniería Física","0":null,"I":94,"II":159,"III":80.0,"IV":13.0,"V":3.0,"VI":2.0,"SEMESTRE":"2018-2"},{"ID":107,"PROGRAMA":"Ingeniería Física (Básicos ingenieria)","0":null,"I":5,"II":6,"III":1.0,"IV":1.0,"V":null,"VI":null,"SEMESTRE":"2018-2"},{"ID":108,"PROGRAMA":"Ingeniería de Sistemas y Computación","0":null,"I":174,"II":354,"III":158.0,"IV":47.0,"V":13.0,"VI":7.0,"SEMESTRE":"2018-2"},{"ID":109,"PROGRAMA":"Ingeniería de Sistemas y Computación (Básicos ingeniería)","0":null,"I":8,"II":12,"III":1.0,"IV":null,"V":null,"VI":1.0,"SEMESTRE":"2018-2"},{"ID":110,"PROGRAMA":"Ingeniería de Sistemas y Computación (Convenio Cuba)","0":null,"I":11,"II":15,"III":6.0,"IV":4.0,"V":1.0,"VI":null,"SEMESTRE":"2018-2"},{"ID":111,"PROGRAMA":"Ingeniería de Sistemas y Computación (Nocturno)","0":null,"I":37,"II":81,"III":70.0,"IV":36.0,"V":5.0,"VI":2.0,"SEMESTRE":"2018-2"},{"ID":112,"PROGRAMA":"Ingeniería Electrónica (Diurna)","0":null,"I":54,"II":70,"III":34.0,"IV":13.0,"V":6.0,"VI":1.0,"SEMESTRE":"2019-1"},{"ID":113,"PROGRAMA":"Ingeniería Electrónica (Nocturno)","0":null,"I":10,"II":43,"III":22.0,"IV":23.0,"V":null,"VI":2.0,"SEMESTRE":"2019-1"},{"ID":114,"PROGRAMA":"Ingeniería Eléctrica","0":1.0,"I":295,"II":428,"III":184.0,"IV":41.0,"V":12.0,"VI":1.0,"SEMESTRE":"2019-1"},{"ID":115,"PROGRAMA":"Ingeniería Física","0":null,"I":104,"II":160,"III":66.0,"IV":12.0,"V":2.0,"VI":3.0,"SEMESTRE":"2019-1"},{"ID":116,"PROGRAMA":"Ingeniería de Sistemas y Computación","0":null,"I":173,"II":355,"III":151.0,"IV":52.0,"V":15.0,"VI":5.0,"SEMESTRE":"2019-1"},{"ID":117,"PROGRAMA":"Ingeniería de Sistemas y Computación (Convenio Cuba)","0":null,"I":11,"II":17,"III":5.0,"IV":3.0,"V":1.0,"VI":null,"SEMESTRE":"2019-1"},{"ID":118,"PROGRAMA":"Ingeniería de Sistemas y Computación (Nocturno)","0":null,"I":50,"II":111,"III":83.0,"IV":33.0,"V":7.0,"VI":1.0,"SEMESTRE":"2019-1"},{"ID":119,"PROGRAMA":"Tecnología en Desarrollo de Software","0":null,"I":11,"II":14,"III":6.0,"IV":1.0,"V":null,"VI":null,"SEMESTRE":"2019-1"},{"ID":120,"PROGRAMA":"Ingeniería Electrónica (Diurna)","0":null,"I":47,"II":71,"III":29.0,"IV":16.0,"V":7.0,"VI":2.0,"SEMESTRE":"2019-2"},{"ID":121,"PROGRAMA":"Ingeniería Electrónica (Nocturno)","0":null,"I":7,"II":37,"III":19.0,"IV":23.0,"V":1.0,"VI":1.0,"SEMESTRE":"2019-2"},{"ID":122,"PROGRAMA":"Ingeniería Eléctrica","0":1.0,"I":303,"II":410,"III":166.0,"IV":38.0,"V":11.0,"VI":1.0,"SEMESTRE":"2019-2"},{"ID":123,"PROGRAMA":"Ingeniería Física","0":null,"I":104,"II":160,"III":65.0,"IV":14.0,"V":2.0,"VI":3.0,"SEMESTRE":"2019-2"},{"ID":124,"PROGRAMA":"Ingeniería de Sistemas y Computación","0":null,"I":184,"II":339,"III":147.0,"IV":52.0,"V":15.0,"VI":5.0,"SEMESTRE":"2019-2"},{"ID":125,"PROGRAMA":"Ingeniería de Sistemas y Computación (Convenio Cuba)","0":null,"I":10,"II":15,"III":5.0,"IV":3.0,"V":1.0,"VI":null,"SEMESTRE":"2019-2"},{"ID":126,"PROGRAMA":"Ingeniería de Sistemas y Computación (Nocturno)","0":null,"I":51,"II":112,"III":71.0,"IV":39.0,"V":6.0,"VI":1.0,"SEMESTRE":"2019-2"},{"ID":127,"PROGRAMA":"Tecnología en Desarrollo de Software","0":null,"I":8,"II":10,"III":5.0,"IV":null,"V":null,"VI":null,"SEMESTRE":"2019-2"},{"ID":128,"PROGRAMA":"Ingeniería Electrónica (Diurna)","0":null,"I":61,"II":88,"III":47.0,"IV":19.0,"V":8.0,"VI":2.0,"SEMESTRE":"2020-1"},{"ID":129,"PROGRAMA":"Ingeniería Electrónica (Nocturno)","0":null,"I":7,"II":31,"III":15.0,"IV":20.0,"V":1.0,"VI":1.0,"SEMESTRE":"2020-1"},{"ID":130,"PROGRAMA":"Ingeniería Eléctrica","0":1.0,"I":308,"II":416,"III":167.0,"IV":32.0,"V":10.0,"VI":1.0,"SEMESTRE":"2020-1"},{"ID":131,"PROGRAMA":"Ingeniería Física","0":null,"I":109,"II":164,"III":64.0,"IV":17.0,"V":2.0,"VI":3.0,"SEMESTRE":"2020-1"},{"ID":132,"PROGRAMA":"Ingeniería de Sistemas y Computación","0":null,"I":192,"II":345,"III":157.0,"IV":58.0,"V":12.0,"VI":6.0,"SEMESTRE":"2020-1"},{"ID":133,"PROGRAMA":"Ingeniería de Sistemas y Computación (Convenio Cuba)","0":null,"I":10,"II":13,"III":4.0,"IV":3.0,"V":1.0,"VI":null,"SEMESTRE":"2020-1"},{"ID":134,"PROGRAMA":"Ingeniería de Sistemas y Computación (Nocturno)","0":null,"I":61,"II":126,"III":77.0,"IV":48.0,"V":4.0,"VI":2.0,"SEMESTRE":"2020-1"},{"ID":135,"PROGRAMA":"Tecnología en Desarrollo de Software","0":null,"I":11,"II":23,"III":15.0,"IV":1.0,"V":null,"VI":null,"SEMESTRE":"2020-1"},{"ID":136,"PROGRAMA":"Ingeniería Electrónica (Diurna)","0":null,"I":72,"II":96,"III":51.0,"IV":17.0,"V":8.0,"VI":2.0,"SEMESTRE":"2020-2"},{"ID":137,"PROGRAMA":"Ingeniería Electrónica (Nocturno)","0":null,"I":6,"II":25,"III":10.0,"IV":13.0,"V":1.0,"VI":1.0,"SEMESTRE":"2020-2"},{"ID":138,"PROGRAMA":"Ingeniería Eléctrica","0":1.0,"I":353,"II":435,"III":160.0,"IV":38.0,"V":11.0,"VI":1.0,"SEMESTRE":"2020-2"},{"ID":139,"PROGRAMA":"Ingeniería Física","0":null,"I":112,"II":165,"III":70.0,"IV":20.0,"V":2.0,"VI":3.0,"SEMESTRE":"2020-2"},{"ID":140,"PROGRAMA":"Ingeniería de Sistemas y Computación","0":null,"I":209,"II":358,"III":170.0,"IV":53.0,"V":16.0,"VI":7.0,"SEMESTRE":"2020-2"},{"ID":141,"PROGRAMA":"Ingeniería de Sistemas y Computación (Convenio Cuba)","0":null,"I":10,"II":13,"III":4.0,"IV":3.0,"V":1.0,"VI":null,"SEMESTRE":"2020-2"},{"ID":142,"PROGRAMA":"Ingeniería de Sistemas y Computación (Nocturno)","0":null,"I":76,"II":142,"III":77.0,"IV":41.0,"V":6.0,"VI":3.0,"SEMESTRE":"2020-2"},{"ID":143,"PROGRAMA":"Tecnología en Desarrollo de Software","0":null,"I":9,"II":17,"III":14.0,"IV":null,"V":null,"VI":null,"SEMESTRE":"2020-2"},{"ID":144,"PROGRAMA":"Ingeniería Electrónica (Diurna)","0":null,"I":92,"II":111,"III":54.0,"IV":21.0,"V":9.0,"VI":2.0,"SEMESTRE":"2021-1"},{"ID":145,"PROGRAMA":"Ingeniería Electrónica (Nocturno)","0":null,"I":4,"II":21,"III":10.0,"IV":10.0,"V":1.0,"VI":1.0,"SEMESTRE":"2021-1"},{"ID":146,"PROGRAMA":"Ingeniería Eléctrica","0":1.0,"I":347,"II":415,"III":144.0,"IV":32.0,"V":9.0,"VI":1.0,"SEMESTRE":"2021-1"},{"ID":147,"PROGRAMA":"Ingeniería Física","0":null,"I":103,"II":157,"III":67.0,"IV":15.0,"V":3.0,"VI":2.0,"SEMESTRE":"2021-1"},{"ID":148,"PROGRAMA":"Ingeniería de Sistemas y Computación","0":null,"I":199,"II":354,"III":167.0,"IV":56.0,"V":16.0,"VI":7.0,"SEMESTRE":"2021-1"},{"ID":149,"PROGRAMA":"Ingeniería de Sistemas y Computación (Convenio Cuba)","0":null,"I":10,"II":13,"III":3.0,"IV":3.0,"V":1.0,"VI":null,"SEMESTRE":"2021-1"},{"ID":150,"PROGRAMA":"Ingeniería de Sistemas y Computación (Nocturno)","0":null,"I":78,"II":148,"III":70.0,"IV":32.0,"V":3.0,"VI":2.0,"SEMESTRE":"2021-1"},{"ID":151,"PROGRAMA":"Tecnología en Desarrollo de Software","0":null,"I":6,"II":11,"III":11.0,"IV":null,"V":null,"VI":null,"SEMESTRE":"2021-1"},{"ID":152,"PROGRAMA":"Ingeniería Electrónica (Diurna)","0":1.0,"I":91,"II":115,"III":60.0,"IV":20.0,"V":9.0,"VI":3.0,"SEMESTRE":"2021-2"},{"ID":153,"PROGRAMA":"Ingeniería Electrónica (Nocturno)","0":null,"I":4,"II":20,"III":6.0,"IV":5.0,"V":null,"VI":null,"SEMESTRE":"2021-2"},{"ID":154,"PROGRAMA":"Ingeniería Eléctrica","0":null,"I":349,"II":424,"III":141.0,"IV":32.0,"V":9.0,"VI":1.0,"SEMESTRE":"2021-2"},{"ID":155,"PROGRAMA":"Ingeniería Física","0":null,"I":98,"II":156,"III":65.0,"IV":18.0,"V":2.0,"VI":2.0,"SEMESTRE":"2021-2"},{"ID":156,"PROGRAMA":"Ingeniería de Sistemas y Computación","0":null,"I":202,"II":373,"III":178.0,"IV":51.0,"V":16.0,"VI":7.0,"SEMESTRE":"2021-2"},{"ID":157,"PROGRAMA":"Ingeniería de Sistemas y Computación (Nocturno)","0":null,"I":89,"II":168,"III":84.0,"IV":34.0,"V":5.0,"VI":2.0,"SEMESTRE":"2021-2"},{"ID":158,"PROGRAMA":"Tecnología en Desarrollo de Software","0":null,"I":18,"II":28,"III":16.0,"IV":2.0,"V":null,"VI":null,"SEMESTRE":null}]